lfepy/__init__.py
lfepy/Descriptor/BPPC.py
lfepy/Descriptor/GDP.py
lfepy/Descriptor/GDP2.py
lfepy/Descriptor/GLTP.py
lfepy/Descriptor/IWBC.py
lfepy/Descriptor/LAP.py
lfepy/Descriptor/LBP.py
lfepy/Descriptor/LDN.py
lfepy/Descriptor/LDTP.py
lfepy/Descriptor/LDiP.py
lfepy/Descriptor/LDiPv.py
lfepy/Descriptor/LFD.py
lfepy/Descriptor/LGBPHS.py
lfepy/Descriptor/LGDiP.py
lfepy/Descriptor/LGIP.py
lfepy/Descriptor/LGP.py
lfepy/Descriptor/LGTrP.py
lfepy/Descriptor/LMP.py
lfepy/Descriptor/LPQ.py
lfepy/Descriptor/LTeP.py
lfepy/Descriptor/LTrP.py
lfepy/Descriptor/MBC.py
lfepy/Descriptor/MBP.py
lfepy/Descriptor/MRELBP.py
lfepy/Descriptor/MTP.py
lfepy/Descriptor/PHOG.py
lfepy/Descriptor/WLD.py
lfepy/Descriptor/__init__.py
lfepy/Helper/NILBP_Image_ct.py
lfepy/Helper/NewRDLBP_Image.py
lfepy/Helper/RDLBP_Image_SmallestRadiusOnly.py
lfepy/Helper/__init__.py
lfepy/Helper/bin_matrix.py
lfepy/Helper/cirInterpSingleRadiusNew.py
lfepy/Helper/cirInterpSingleRadius_ct.py
lfepy/Helper/construct_Gabor_filters.py
lfepy/Helper/descriptor_LBP.py
lfepy/Helper/descriptor_LDN.py
lfepy/Helper/descriptor_LPQ.py
lfepy/Helper/descriptor_PHOG.py
lfepy/Helper/dgauss.py
lfepy/Helper/filter_image_with_Gabor_bank.py
lfepy/Helper/gabor_filter.py
lfepy/Helper/gauss.py
lfepy/Helper/gauss_gradient.py
lfepy/Helper/get_mapping.py
lfepy/Helper/get_mapping_info_ct.py
lfepy/Helper/get_mapping_mrelbp.py
lfepy/Helper/low_pass_filter.py
lfepy/Helper/lxp_phase.py
lfepy/Helper/monofilt.py
lfepy/Helper/phase_cong3.py
lfepy/Helper/phogDescriptor_hist.py
lfepy/Helper/roundn.py
lfepy/Helper/view_as_windows.py
lfepy/Validator/__init__.py
lfepy/Validator/validate_DGLP.py
lfepy/Validator/validate_L.py
lfepy/Validator/validate_N.py
lfepy/Validator/validate_T.py
lfepy/Validator/validate_angle.py
lfepy/Validator/validate_bin.py
lfepy/Validator/validate_epsi.py
lfepy/Validator/validate_image.py
lfepy/Validator/validate_kwargs.py
lfepy/Validator/validate_mappingType.py
lfepy/Validator/validate_mask_GDP.py
lfepy_gpu-1.0.0.dist-info/LICENSE.md
lfepy_gpu-1.0.0.dist-info/METADATA
lfepy_gpu-1.0.0.dist-info/WHEEL
lfepy_gpu-1.0.0.dist-info/top_level.txt
lfepy_gpu-1.0.0.dist-info/RECORD
