Metadata-Version: 2.1
Name: lfepy-gpu
Version: 1.0.0
Summary: lfepy is a Python package for local feature extraction.
Home-page: https://github.com/lfepy/lfepy-gpu
Author: Dr. Prof. Khalid M. Hosny, MSc. Mahmoud A. Mohamed
Author-email: lfepy@gmail.com
Classifier: Programming Language :: Python :: 3
Classifier: License :: OSI Approved :: MIT License
Classifier: Operating System :: OS Independent
Requires-Python: >=3.0
License-File: LICENSE.md
Requires-Dist: cupy-cuda11x>=13.3.0
Requires-Dist: numpy>=1.26.4
Requires-Dist: scipy>=1.13.0
Requires-Dist: scikit-image>=0.23.2
